[
    {
        "name": "乾卦",
        "imageName": "乾卦",
        "explanations": [
            "乾。元亨利贞。\r\n象曰：天行健，君子以自强不息。\r\n①时运：临事刚健，自强不息。\r\n②财运：施比。\r\n③家宅：积善。\r\n④身体：保健。",
            "初九。潜龙勿用。\r\n象曰：天行健，君子以自强不息。\r\n①时运：临事刚健，自强不息。\r\n②财运：施比。\r\n③家宅：积善。\r\n④身体：保健。",
            "九二。见龙在田，利见大人。\r\n象曰：天行健，君子以自强不息。\r\n时运：临事刚健，自强不息。\r\n财运：施比。\r\n家宅：积善。\r\n身体：保健。",
            "九三。君子终日乾乾，夕惕若；历，无咎。\r\n象曰：天行健，君子以自强不息。\r\n时运：临事刚健，自强不息。\r\n财运：施比。\r\n家宅：积善。\r\n身体：保健。",
            "九四。或跃在渊，无咎。\r\n象曰：天行健，君子以自强不息。\r\n时运：临事刚健，自强不息。\r\n财运：施比。\r\n家宅：积善。\r\n身体：保健。",
            "九五。飞龙在天，利见大人。\r\n象曰：天行健，君子以自强不息。\r\n时运：临事刚健，自强不息。\r\n财运：施比。\r\n家宅：积善。\r\n身体：保健。",
            "上九。亢龙有悔。\r\n象曰：天行健，君子以自强不息。\r\n时运：临事刚健，自强不息。\r\n财运：施比。\r\n家宅：积善。\r\n身体：保健。"
        ]
    },
    {
        "name": "坤",
        "imageName": "坤卦",
        "explanations": [
            "乾。元亨利贞。\r\n象曰：天行健，君子以自强不息。\r\n①时运：临事刚健，自强不息。\r\n②财运：施比。\r\n③家宅：积善。\r\n④身体：保健。",
            "初九。潜龙勿用。\r\n象曰：天行健，君子以自强不息。\r\n①时运：临事刚健，自强不息。\r\n②财运：施比。\r\n③家宅：积善。\r\n④身体：保健。",
            "九二。见龙在田，利见大人。\r\n象曰：天行健，君子以自强不息。\r\n时运：临事刚健，自强不息。\r\n财运：施比。\r\n家宅：积善。\r\n身体：保健。",
            "九三。君子终日乾乾，夕惕若；历，无咎。\r\n 象曰：天行健，君子以自强不息。\r\n时运：临事刚健，自强不息。\r\n财运：施比。\r\n家宅：积善。\r\n身体：保健。",
            "九四。或跃在渊，无咎。\r\n象曰：天行健，君子以自强不息。\r\n时运：临事刚健，自强不息。\r\n财运：施比。\r\n家宅：积善。\r\n身体：保健。",
            "九五。飞龙在天，利见大人。\r\n象曰：天行健，君子以自强不息。\r\n时运：临事刚健，自强不息。\r\n财运：施比。\r\n家宅：积善。\r\n身体：保健。",
            "上九。亢龙有悔。\r\n象曰：天行健，君子以自强不息。\r\n时运：临事刚健，自强不息。\r\n财运：施比。\r\n家宅：积善。\r\n身体：保健。"
        ]
    }
]
